jbom/__init__.py
jbom/__main__.py
jbom/__version__.py
jbom/api.py
jbom/cli/annotate_command.py
jbom/cli/bom_command.py
jbom/cli/commands.py
jbom/cli/common.py
jbom/cli/formatting.py
jbom/cli/inventory_command.py
jbom/cli/inventory_search_command.py
jbom/cli/main.py
jbom/cli/main_old.py
jbom/cli/pos_command.py
jbom/cli/search_command.py
jbom/common/__init__.py
jbom/common/config.py
jbom/common/config_fabricators.py
jbom/common/constants.py
jbom/common/fabricators.py
jbom/common/fields.py
jbom/common/fields_system.py
jbom/common/generator.py
jbom/common/options.py
jbom/common/output.py
jbom/common/packages.py
jbom/common/sexp_parser.py
jbom/common/types.py
jbom/common/utils.py
jbom/common/values.py
jbom/config/defaults.yaml
jbom/config/fabricators/generic.fab.yaml
jbom/config/fabricators/jlc.fab.yaml
jbom/config/fabricators/pcbway.fab.yaml
jbom/config/fabricators/seeed.fab.yaml
jbom/generators/__init__.py
jbom/generators/bom.py
jbom/generators/pos.py
jbom/loaders/__init__.py
jbom/loaders/inventory.py
jbom/loaders/jlc_loader.py
jbom/loaders/pcb.py
jbom/loaders/pcb_model.py
jbom/loaders/project_inventory.py
jbom/loaders/schematic.py
jbom/processors/__init__.py
jbom/processors/annotator.py
jbom/processors/classifier.py
jbom/processors/component_types.py
jbom/processors/inventory_enricher.py
jbom/processors/inventory_matcher.py
jbom/processors/search_result_scorer.py
jbom/sch_api/model.py
jbom/search/__init__.py
jbom/search/filter.py
jbom/search/mouser.py
jbom-4.2.0.dist-info/licenses/LICENSE
jbom-4.2.0.dist-info/METADATA
jbom-4.2.0.dist-info/WHEEL
jbom-4.2.0.dist-info/entry_points.txt
jbom-4.2.0.dist-info/top_level.txt
jbom-4.2.0.dist-info/RECORD
