Metadata-Version: 2.4
Name: jbom
Version: 4.2.0
Summary: Intelligent KiCad Bill of Materials generator with inventory matching
Author-email: John Plocher <John.Plocher@gmail.com>
License-Expression: AGPL-3.0-only
Project-URL: Homepage, https://github.com/plocher/jBOM
Project-URL: Documentation, https://github.com/plocher/jBOM#readme
Project-URL: Repository, https://github.com/plocher/jBOM.git
Project-URL: Issues, https://github.com/plocher/jBOM/issues
Keywords: kicad,bom,bill-of-materials,pcb,electronics,inventory
Classifier: Development Status :: 5 - Production/Stable
Classifier: Environment :: Console
Classifier: Intended Audience :: Developers
Classifier: Intended Audience :: Manufacturing
Classifier: Operating System :: OS Independent
Classifier: Programming Language :: Python :: 3
Classifier: Programming Language :: Python :: 3.9
Classifier: Programming Language :: Python :: 3.10
Classifier: Programming Language :: Python :: 3.11
Classifier: Programming Language :: Python :: 3.12
Classifier: Topic :: Scientific/Engineering
Classifier: Topic :: Office/Business
Classifier: Topic :: Utilities
Requires-Python: >=3.9
License-File: LICENSE
Requires-Dist: sexpdata>=0.0.3
Requires-Dist: PyYAML>=5.4.0
Provides-Extra: excel
Requires-Dist: openpyxl>=3.0; extra == "excel"
Provides-Extra: numbers
Requires-Dist: numbers-parser>=3.0; extra == "numbers"
Provides-Extra: search
Requires-Dist: requests>=2.28.0; extra == "search"
Provides-Extra: dev
Requires-Dist: build>=0.10.0; extra == "dev"
Requires-Dist: twine>=4.0.0; extra == "dev"
Requires-Dist: wheel>=0.37.0; extra == "dev"
Provides-Extra: all
Requires-Dist: openpyxl>=3.0; extra == "all"
Requires-Dist: numbers-parser>=3.0; extra == "all"
Requires-Dist: requests>=2.28.0; extra == "all"
Dynamic: license-file
